MANIFEST.in
README.md
setup.py
tellandroid
scripts/tellandroid
tellandroid/__init__.py
tellandroid/handlers.py
tellandroid/telnet.py
tellandroid.egg-info/PKG-INFO
tellandroid.egg-info/SOURCES.txt
tellandroid.egg-info/dependency_links.txt
tellandroid.egg-info/requires.txt
tellandroid.egg-info/top_level.txt