Metadata-Version: 1.0
Name: tellandroid
Version: 0.1.0
Summary: A set of utilities to make it easier to work with the android emulator telnet protocol.
Home-page: http://rainfalldesign.com/
Author: Vitaly Babiy
Author-email: vbabiy86@gmail.com
License: UNKNOWN
Platform: UNKNOWN
